<?xml version="1.0" encoding="UTF-8"?>
<objects serializationModel="Studio.02.02.00">
	<object class="AudioFile" id="{0631385a-7fb3-4989-b674-6a276b3af9a0}">
		<property name="assetPath">
			<value>Efectos/Gabriel.wav</value>
		</property>
		<property name="frequencyInKHz">
			<value>44.0999985</value>
		</property>
		<property name="channelCount">
			<value>2</value>
		</property>
		<property name="length">
			<value>2.4671201814058956</value>
		</property>
		<relationship name="masterAssetFolder">
			<destination>{68578b9e-cc60-4861-a58d-dde428447113}</destination>
		</relationship>
	</object>
</objects>
